pylyglot/__init__.py
pylyglot-1.1.1.dist-info/licenses/LICENSE
pylyglot-1.1.1.dist-info/METADATA
pylyglot-1.1.1.dist-info/WHEEL
pylyglot-1.1.1.dist-info/top_level.txt
pylyglot-1.1.1.dist-info/RECORD
