Metadata-Version: 2.4
Name: pylyglot
Version: 1.1.1
Summary: A lightweight, extensible i18n utility for Python projects
Author: Aaquinas
License: MIT License
Project-URL: Homepage, https://gitlab.com/Aaquinas/pylyglot
Requires-Python: >=3.7
License-File: LICENSE
Dynamic: license-file
